{
  "New Developments": {
    "description": "Today's controversies from across the news spectrum, updated automatically",
    "updatedAt": "2026-07-13T13:10:58.832Z",
    "keywords": {
      "Ro Khanna": {
        "weight": 3,
        "description": "In 3 outlets across the spectrum (since 2026-07-12)"
      },
      "Air Force One reporting": {
        "weight": 1,
        "description": "In 3 outlets across the spectrum (since 2026-07-13)"
      },
      "Bipartisan Housing Bill": {
        "weight": 1,
        "description": "In 3 outlets across the spectrum (since 2026-07-12)"
      },
      "New York Times Journalists": {
        "weight": 1,
        "description": "In 3 outlets across the spectrum (since 2026-07-12)"
      },
      "Strait of Hormuz": {
        "weight": 2,
        "description": "In 5 outlets across the spectrum (since 2026-07-13)"
      },
      "Platner": {
        "weight": 1,
        "description": "In 5 outlets across the spectrum (since 2026-07-13)"
      },
      "Armed Israeli Settlers": {
        "weight": 1,
        "description": "In 3 outlets across the spectrum (since 2026-07-13)"
      }
    }
  }
}
